{"script_excerpt":"const ROTATION_SPEED = 0.5 // Speed of logo rotation in radians per second\nconst DOOR_ANIMATION_SPEED = 2.0 // Speed of door animation\n\n// Configure audio slots\napp.configure([\n\t{\n\t\tkey: 'doorSound',\n\t\ttype: 'file',\n\t\tkind: 'audio',\n\t\tlabel: 'Door Sound Effect'\n\t},\n\t{\n\t\tkey: 'fridgeHum',\n\t\ttype: 'file',\n\t\tkind: 'audio',\n\t\tlabel: 'Fridge Ambient Hum'\n\t}\n])\n\n// Initialize state\napp.state = {\n\tisOpen: false,\n\tcurrentRotation: 0,\n\ttargetRotation: 0\n}\n\n// Get references to objects\nconst logo = app.get('$HYPER')\nconst door = app.get('HyperFridgeDoor')\nconsole.log('Door ID:', door?.id)\n\n// Create audio instances\nconst doorSound = app.create('audio', {\n\tsrc: props.doorSound?.url,\n\tvolume: 0.6,\n\tgroup: 'sfx',\n\tspatial: true\n})\n\nconst fridgeHum = app.create('audio', {\n\tsrc: props.fridgeHum?.url,\n\tvolume: 0.2,\n\tmaxDistance: 10,\n\trefDistance: 1,\n\trolloffFactor: 1,\n\tgroup: 'sfx',\n\tspatial: true,\n\tloop: true\n})\n\n// Create a simple action for the door\nconst action = app.create('action')\naction.label = 'Open'\naction.position.set(1, 0, 0)\naction.distance = 2\n\n// Add the action and sounds to the door if we have it\nif (door) {\n\tdoor.add(action)\n\tdoor.add(doorSound)\n\tdoor.add(fridgeHum)\n\t// Start the ambient hum\n\tif (fridgeHum) {\n\t\tfridgeHum.play()\n\t}\n} else {\n\tconsole.log('Door not found, adding action to app')\n\tapp.add(action)\n}\n\n// Simple toggle action\naction.onTrigger = () => {\n\tconsole.log('Action triggered')\n\tapp.state.isOpen = !app.state.isOpen\n\tapp.state.targetRotation = app.state.isOpen ? -Math.PI * 0.5 : 0 // Negative for opposite direction\n\tconsole.log('New state:', app.state.isOpen ? 'open' : 'closed')\n\taction.label = app.state.isOpen ? 'Close' : 'Open'\n\n\t// Play door sound\n\tif (doorSound) {\n\t\tdoorSound.stop() // Stop any currently playing sound\n\t\tdoorSound.currentTime = 0 // Reset to start\n\t\tdoorSound.play()\n\t}\n}\n\n// Rotate logo and animate door\napp.on('update', (dt) => {\n\t// Logo rotation\n\tif (logo) {\n\t\tlogo.rotation.y += ROTATION_SPEED * dt\n\t}\n\n\t// Smooth door animation\n","script_path":"assets/44c8ab04eda15e4d03c3bcbec6e1fbc5c041881aea7b5a856c39bc1a0b967543.js","source_files":[{"path":"assets/1305e6ae6851665f0e0c2d74ff02ccecbdba6025f0118ba31469957395321240.mp3","size_bytes":978432},{"path":"assets/4025cab7040fa4ef642158c576f74accaaf762c33141156420f3268da11f4c74.glb","size_bytes":3112188},{"path":"assets/44c8ab04eda15e4d03c3bcbec6e1fbc5c041881aea7b5a856c39bc1a0b967543.js","size_bytes":2411},{"path":"assets/d60648b9091c00e460545dce3cef7b88c0d643d0a864424f715a878c2ad3661a.png","size_bytes":147},{"path":"assets/e54ef172155989794da0e21f24eecf426fcd3622f144f985915384db3e3f13f7.mp3","size_bytes":24960},{"path":"blueprint.json","size_bytes":910},{"path":"manifest.json","size_bytes":1293}],"props":{"doorSound":{"type":"audio","name":"door_close.mp3","url":"asset://e54ef172155989794da0e21f24eecf426fcd3622f144f985915384db3e3f13f7.mp3"},"fridgeHum":{"type":"audio","name":"fridge_hum.mp3","url":"asset://1305e6ae6851665f0e0c2d74ff02ccecbdba6025f0118ba31469957395321240.mp3"}},"asset_files":["1305e6ae6851665f0e0c2d74ff02ccecbdba6025f0118ba31469957395321240.mp3","4025cab7040fa4ef642158c576f74accaaf762c33141156420f3268da11f4c74.glb","44c8ab04eda15e4d03c3bcbec6e1fbc5c041881aea7b5a856c39bc1a0b967543.js","d60648b9091c00e460545dce3cef7b88c0d643d0a864424f715a878c2ad3661a.png","e54ef172155989794da0e21f24eecf426fcd3622f144f985915384db3e3f13f7.mp3"],"blueprint_path":"blueprint.json"}