{"script_excerpt":"const cube = app.get(\"$root\")\n\nlet isRolling = false;\nlet rollDuration = 2;\nlet elapsedTime = 0;\nlet randomRotation = { x: 0, y: 0, z: 0 };\n\ncube.onPointerDown = () => {\n  if (!isRolling) {\n    isRolling = true;\n    elapsedTime = 0;\n    randomRotation = {\n      x: 10,\n      y: 2,\n      z: 8,\n    };\n  }\n};\n\napp.on(\"update\", (delta) => {\n  if (isRolling) {\n    elapsedTime += delta;\n    let progress = elapsedTime / rollDuration;\n    if (progress < 1) {\n      let easingFactor = 1 - progress;\n      cube.rotation.x += randomRotation.x * delta * easingFactor;\n      cube.rotation.y += randomRotation.y * delta * easingFactor;\n      cube.rotation.z += randomRotation.z * delta * easingFactor;\n    } else {\n      isRolling = false;\n    }\n  }\n});\n","script_path":"assets/926d8830c2716bb45ba302bc77f0efdbbcea2df79873faa747cafe7a2724a159.js","source_files":[{"path":"assets/311af40e321ccade1f2a8722a99e410917af4e8bba79beeb36acf62b4467a1d6.glb","size_bytes":258836},{"path":"assets/926d8830c2716bb45ba302bc77f0efdbbcea2df79873faa747cafe7a2724a159.js","size_bytes":776},{"path":"blueprint.json","size_bytes":385},{"path":"manifest.json","size_bytes":525}],"asset_files":["311af40e321ccade1f2a8722a99e410917af4e8bba79beeb36acf62b4467a1d6.glb","926d8830c2716bb45ba302bc77f0efdbbcea2df79873faa747cafe7a2724a159.js"],"blueprint_path":"blueprint.json"}